LICENSE
MANIFEST.in
README.rst
setup.py
django_ohm2_permissions_light.egg-info/PKG-INFO
django_ohm2_permissions_light.egg-info/SOURCES.txt
django_ohm2_permissions_light.egg-info/dependency_links.txt
django_ohm2_permissions_light.egg-info/requires.txt
django_ohm2_permissions_light.egg-info/top_level.txt
docs/INFO.txt
ohm2_permissions_light/__init__.py
ohm2_permissions_light/admin.py
ohm2_permissions_light/apps.py
ohm2_permissions_light/context_processors.py
ohm2_permissions_light/decorators.py
ohm2_permissions_light/definitions.py
ohm2_permissions_light/dispatcher.py
ohm2_permissions_light/errors.py
ohm2_permissions_light/managers.py
ohm2_permissions_light/middlewares.py
ohm2_permissions_light/models.py
ohm2_permissions_light/serializers.py
ohm2_permissions_light/settings.py
ohm2_permissions_light/tests.py
ohm2_permissions_light/urls.py
ohm2_permissions_light/utils.py
ohm2_permissions_light/views.py
ohm2_permissions_light/management/__init__.py
ohm2_permissions_light/management/commands/__init__.py
ohm2_permissions_light/management/commands/ohm2_permissions_light_test_command.py
ohm2_permissions_light/migrations/__init__.py
ohm2_permissions_light/migrations/__pycache__/__init__.cpython-35.pyc